.gitattributes
.gitignore
LICENSE
README.md
setup.py
pyLearnAlgorithms/__init__.py
pyLearnAlgorithms/graph_view.py
pyLearnAlgorithms/linear_regression.py
pyLearnAlgorithms/logistic_regression.py
pyLearnAlgorithms/lr_neural_network.py
pyLearnAlgorithms/model_analysis.py
pyLearnAlgorithms/polynomial_regression.py
pyLearnAlgorithms/split_data.py
pyLearnAlgorithms.egg-info/PKG-INFO
pyLearnAlgorithms.egg-info/SOURCES.txt
pyLearnAlgorithms.egg-info/dependency_links.txt
pyLearnAlgorithms.egg-info/requires.txt
pyLearnAlgorithms.egg-info/top_level.txt