Metadata-Version: 2.1
Name: pyLearnAlgorithms
Version: 0.3.5
Summary: Python Machine Learning algorithms based on Numpy, Scipy and MatPlotLib.
Home-page: https://github.com/Alyssonmach/pyLearnAlgorithms
Author: Alysson Machado
Author-email: alysson.barbosa@ee.ufcg.edu.br
License: MIT License
Keywords: Machine Learning,Regression,Classification,NeuralNetwork
Platform: UNKNOWN
